toucai/__init__.py
toucai/cli.py
toucai/toucai.py
toucai-0.1.0.dist-info/AUTHORS.rst
toucai-0.1.0.dist-info/METADATA
toucai-0.1.0.dist-info/WHEEL
toucai-0.1.0.dist-info/entry_points.txt
toucai-0.1.0.dist-info/top_level.txt
toucai-0.1.0.dist-info/RECORD
